odoo/addons/account_invoice_margin_sale_sync/README.rst
odoo/addons/account_invoice_margin_sale_sync/__init__.py
odoo/addons/account_invoice_margin_sale_sync/__manifest__.py
odoo/addons/account_invoice_margin_sale_sync/i18n/es.po
odoo/addons/account_invoice_margin_sale_sync/models/__init__.py
odoo/addons/account_invoice_margin_sale_sync/models/account_move.py
odoo/addons/account_invoice_margin_sale_sync/models/res_company.py
odoo/addons/account_invoice_margin_sale_sync/models/res_config_settings.py
odoo/addons/account_invoice_margin_sale_sync/readme/CONFIGURE.rst
odoo/addons/account_invoice_margin_sale_sync/readme/CONTRIBUTORS.rst
odoo/addons/account_invoice_margin_sale_sync/readme/DESCRIPTION.rst
odoo/addons/account_invoice_margin_sale_sync/static/description/icon.png
odoo/addons/account_invoice_margin_sale_sync/static/description/index.html
odoo/addons/account_invoice_margin_sale_sync/views/res_config_settings_views.xml
odoo_addon_account_invoice_margin_sale_sync-15.0.1.0.1.dist-info/METADATA
odoo_addon_account_invoice_margin_sale_sync-15.0.1.0.1.dist-info/WHEEL
odoo_addon_account_invoice_margin_sale_sync-15.0.1.0.1.dist-info/top_level.txt
odoo_addon_account_invoice_margin_sale_sync-15.0.1.0.1.dist-info/RECORD
