Metadata-Version: 2.1
Name: odoo-addon-account_invoice_margin_sale_sync
Version: 15.0.1.0.1
Requires-Python: >=3.8
Requires-Dist: odoo-addon-account_invoice_margin>=15.0dev,<15.1dev
Requires-Dist: odoo>=15.0a,<15.1dev
Summary: Sync invoice margin between invoices and sale orders
Home-page: https://github.com/sygel-technology/sy-margin-analysis
License: AGPL-3
Author: Sygel, Odoo Community Association (OCA)
Author-email: support@odoo-community.org
Classifier: Programming Language :: Python
Classifier: Framework :: Odoo
Classifier: Framework :: Odoo :: 15.0
Classifier: License :: OSI Approved :: GNU Affero General Public License v3
